WaveMote/__init__.py
WaveMote-1.3.0.1.dist-info/LICENSE.txt
WaveMote-1.3.0.1.dist-info/METADATA
WaveMote-1.3.0.1.dist-info/WHEEL
WaveMote-1.3.0.1.dist-info/top_level.txt
WaveMote-1.3.0.1.dist-info/RECORD
