Metadata-Version: 2.1
Name: WaveMote
Version: 1.3.0.1
Summary: A Gestures based Hand Controlled Virtual Mouse
Home-page: https://github.com/bharathguntreddi3/WaveMote.git
Author: Bharath Guntreddi
Author-email: guntreddibharath@gmail.com
License: MIT
Keywords: WaveMote
Platform: UNKNOWN
Classifier: Development Status :: 5 - Production/Stable
Classifier: Intended Audience :: Education
Classifier: Operating System :: Microsoft :: Windows :: Windows 10
Classifier: License :: OSI Approved :: MIT License
Classifier: Programming Language :: Python :: 3
License-File: LICENSE.txt
